libvis_mods/__init__.py
libvis_mods/build.sh
libvis_mods/cli.py
libvis_mods/develop.sh
libvis_mods/exceptions.py
libvis_mods/imports.py
libvis_mods/init_methods.py
libvis_mods/main.py
libvis_mods/publish.py
libvis_mods/python_hot_reload.py
libvis_mods/utils.py
libvis_mods/config/__init__.py
libvis_mods/config/config_gen.py
libvis_mods/config/paths.py
libvis_mods/download/__init__.py
libvis_mods/download/repository.py
libvis_mods/download/vcs.py
libvis_mods/libvis_dist/__init__.py
libvis_mods/libvis_dist/hooked_cmdclass.py
libvis_mods/libvis_dist/install_cmdclass.py
libvis_mods/libvis_dist/libvis_setup.py
libvis_mods/project-templates/test-interactive.py
libvis_mods/project-templates/test-subprocess.py
libvis_mods/project-templates/test.py
libvis_mods/project-templates/sandbox/packagedMod/MANIFEST.in
libvis_mods/project-templates/sandbox/packagedMod/libvis-mod.conf
libvis_mods/project-templates/sandbox/packagedMod/readme.md
libvis_mods/project-templates/sandbox/packagedMod/back/__init__.py
libvis_mods/project-templates/sandbox/packagedMod/back/main.py
libvis_mods/project-templates/sandbox/packagedMod/back/utils.py
libvis_mods/project-templates/sandbox/packagedMod/front/index.js
libvis_mods/project-templates/sandbox/packagedMod/front/main.coffee
libvis_mods/project-templates/sandbox/packagedMod/front/style.css
libvis_mods/tools/__init__.py
libvis_mods/tools/setuptools_hook.py
libvis_mods/web/.gitignore
libvis_mods/web/LICENSE
libvis_mods/web/README.md
libvis_mods/web/index.html
libvis_mods/web/package.json
libvis_mods/web/webpack-lib.config.coffee
libvis_mods/web/webpack.config.coffee
libvis_mods/web/src/App.coffee
libvis_mods/web/src/App.css
libvis_mods/web/src/index.coffee
libvis_mods/web/src/index.html
libvis_mods/web/src/libvis.coffee
libvis_mods/web/src/Data/interface.coffee
libvis_mods/web/src/modules/ResponsiveStorageGrid.coffee
libvis_mods/web/src/modules/Widget.coffee
libvis_mods/web/src/modules/error_boundary.coffee
libvis_mods-0.1.12.dist-info/METADATA
libvis_mods-0.1.12.dist-info/WHEEL
libvis_mods-0.1.12.dist-info/entry_points.txt
libvis_mods-0.1.12.dist-info/top_level.txt
libvis_mods-0.1.12.dist-info/RECORD
