Metadata-Version: 2.1
Name: libvis-mods
Version: 0.1.12
Summary: cli tool to manage libivs modules
Home-page: https://github.com/libvis
Author: Danil Lykov
Author-email: lkvdan@gmail.com
License: MIT
Keywords: tools,libvis,package manager,data,framework,visualization
Platform: UNKNOWN
Requires-Python: >=3.6
Requires-Dist: loguru
Requires-Dist: click
Requires-Dist: libvis
Requires-Dist: watchdog
Requires-Dist: cookiecutter
